config/__init__.py
data/__init__.py
data/data_loader.py
data/extract_data.py
data/read_CEOS_raw.py
data/spcify_param.py
processing/__init__.py
utils/__init__.py
Qiuyue_Hong-0.0.1.dist-info/METADATA
Qiuyue_Hong-0.0.1.dist-info/WHEEL
Qiuyue_Hong-0.0.1.dist-info/top_level.txt
Qiuyue_Hong-0.0.1.dist-info/RECORD
