Metadata-Version: 2.1
Name: Qiuyue-Hong
Version: 0.0.1
Summary: Digital processing of Synthetic aperture radar data.
Author: hqy
Author-email: 369613909@qq.com
License: apache 3.0
Platform: UNKNOWN
Requires: numpy
Requires: matplotlib
